pyfqmr/Simplify.cp312-win_amd64.pyd
pyfqmr/Simplify.h
pyfqmr/Simplify.pyx
pyfqmr/__init__.py
pyfqmr_withuvs-0.2.1.dist-info/LICENSE
pyfqmr_withuvs-0.2.1.dist-info/METADATA
pyfqmr_withuvs-0.2.1.dist-info/WHEEL
pyfqmr_withuvs-0.2.1.dist-info/top_level.txt
pyfqmr_withuvs-0.2.1.dist-info/RECORD
