Metadata-Version: 2.1
Name: pyfqmr_withuvs
Version: 0.2.1
Summary: cython wrapper around C++ library for fast triangular mesh reduction
Home-page: https://github.com/t-montes/pyfqmr
Author: kramer84
License: MIT
Classifier: Development Status :: 2 - Pre-Alpha
Classifier: Intended Audience :: Science/Research
Classifier: Operating System :: OS Independent
Classifier: Programming Language :: Python
Classifier: Topic :: Scientific/Engineering
Classifier: License :: OSI Approved :: MIT License
Classifier: Natural Language :: English
License-File: LICENSE
